{
  "materials": [
    {
      "item": {
        "tag": "c:plates/steel"
      },
      "count": 291
    },
    {
      "item": {
        "tag": "c:plates/iron"
      },
      "count": 166
    },
    {
      "item": {
        "tag": "c:plates/aluminum"
      },
      "count": 125
    },
    {
      "item": {
        "item": "immersiveengineering:stick_steel"
      },
      "count": 83
    },
    {
      "item": {
        "item": "immersiveengineering:component_steel"
      },
      "count": 83
    },
    {
      "item": {
        "item": "tfmg:steel_mechanism"
      },
      "count": 83
    }
  ],
  "result": {
    "type": "gun",
    "id": "suffuse:200rndmk3"
  },
  "type": "tacz:gun_smith_table_crafting"
}