{
  "materials": [
    {
      "item": {
        "tag": "c:plates/steel"
      },
      "count": 182
    },
    {
      "item": {
        "tag": "c:plates/iron"
      },
      "count": 54
    },
    {
      "item": {
        "item": "immersiveengineering:stick_steel"
      },
      "count": 36
    },
    {
      "item": {
        "tag": "minecraft:logs"
      },
      "count": 91
    }
  ],
  "result": {
    "type": "gun",
    "id": "hamster:gew98"
  },
  "type": "tacz:gun_smith_table_crafting"
}